CHANGES.txt
README.txt
setup.cfg
setup.py
src/erp5/__init__.py
src/erp5.recipe.btrepository.egg-info/PKG-INFO
src/erp5.recipe.btrepository.egg-info/SOURCES.txt
src/erp5.recipe.btrepository.egg-info/dependency_links.txt
src/erp5.recipe.btrepository.egg-info/entry_points.txt
src/erp5.recipe.btrepository.egg-info/namespace_packages.txt
src/erp5.recipe.btrepository.egg-info/requires.txt
src/erp5.recipe.btrepository.egg-info/top_level.txt
src/erp5/recipe/__init__.py
src/erp5/recipe/btrepository/__init__.py
src/erp5/recipe/btrepository/doctest.txt
src/erp5/recipe/btrepository/tests.py