Metadata-Version: 1.0
Name: erp5.recipe.btrepository
Version: 0.0.1
Summary: zc.buildout recipe that creates an repository of business template
Home-page: UNKNOWN
Author: Rafael Monnerat
Author-email: rafael@nexedi.com
License: ZPL 2.1
Keywords: bt5 erp5 buildout
Platform: UNKNOWN
Classifier: License :: OSI Approved :: Zope Public License
Classifier: Framework :: Buildout :: Recipe
